setup.py
glamkit_stopspam.egg-info/PKG-INFO
glamkit_stopspam.egg-info/SOURCES.txt
glamkit_stopspam.egg-info/dependency_links.txt
glamkit_stopspam.egg-info/not-zip-safe
glamkit_stopspam.egg-info/top_level.txt
stopspam/__init__.py
stopspam/utils.py
stopspam/forms/__init__.py
stopspam/forms/fields.py
stopspam/forms/forms.py
stopspam/forms/widgets.py