Metadata-Version: 1.0
Name: glamkit-stopspam
Version: 0.5.0
Summary: A Django app to help you filter spam in your forms.
Home-page: http://github.com/glamkit/glamkit-stopspam
Author: Julien Phalip
Author-email: julien@interaction.net.au
License: UNKNOWN
Platform: UNKNOWN
Classifier: Development Status :: 4 - Beta
Classifier: Environment :: Web Environment
Classifier: Intended Audience :: Developers
Classifier: License :: OSI Approved :: BSD License
Classifier: Operating System :: OS Independent
Classifier: Programming Language :: Python
Classifier: Framework :: Django
